{
  "en": {
    "headerIntro": "Thank you for joining us! We would love to hear about your experience. Please take a moment to fill out this short feedback form.",
    "requiredNote": "* Indicates required question",
    "successTitle": "Thank You for Your Feedback!",
    "successMsg": "Thank you for choosing our Jungle Safari! We hope you had a wonderful experience and wish you a great day!",
    "submitAnother": "Submit Another Response",
    "visitorDetails": "Visitor Details",
    "visitorDetailsSub": "Tell us a little about yourself and your safari trip.",
    "visitorName": "Visitor Name",
    "optional": "(Optional)",
    "visitorNamePh": "Enter your full name",
    "occupation": "Occupation",
    "occupationPh": "e.g. Teacher, Farmer, Business",
    "nationality": "Nationality",
    "nationalityPh": "e.g. Indian",
    "address": "Address",
    "addressPh": "Enter your address",
    "addressErr": "Please enter your address.",
    "phone": "Phone / Mobile Number",
    "phonePh": "e.g. 9876543210",
    "phoneErr": "Please enter a valid 10-digit mobile number.",
    "safariDateTime": "Safari Date & Time",
    "safariDateTimeErr": "Please select both the safari date and time (date cannot be in the future).",
    "vehicleGuide": "Vehicle Number / Guide's Name",
    "vehicleGuidePh": "e.g. MH-31-AB-1234 / Ramesh",
    "vehicleGuideErr": "Please enter the vehicle number or guide's name.",
    "q1Title": "1. Overall Safari Experience",
    "q1Sub": "How would you rate your overall jungle safari experience?",
    "optExcellent": "Excellent",
    "optGood": "Good",
    "optAverage": "Average",
    "optPoor": "Poor",
    "selectErr": "Please select an option.",
    "q2Title": "2. Rate Our Services",
    "q2Sub": "Please rate the following services.",
    "scaleHint": "1 = Very Poor · 5 = Excellent",
    "serviceCol": "Service",
    "svc_bookingProcess": "Booking Process",
    "svc_vehicleCondition": "Vehicle Condition & Comfort",
    "svc_guideKnowledge": "Guide / Driver Knowledge & Behavior",
    "svc_safetyMeasures": "Safety Measures",
    "svc_cleanliness": "Cleanliness & Amenities",
    "ratingsErr": "Please rate all five services.",
    "q3Title": "3. Wildlife Sightings",
    "q3Sub": "Did you spot wildlife (animals/birds) during the safari?",
    "wl1": "Yes, more than expected!",
    "wl2": "Yes, I saw a few.",
    "wl3": "No, I hardly saw any.",
    "q4Title": "4. Your Detailed Feedback",
    "q4Sub": "Help us make the safari even better!",
    "likedMost": "What did you like the most about this safari?",
    "likedMostPh": "Share what you enjoyed...",
    "suggestions": "Do you have any suggestions to help us improve our services?",
    "suggestionsPh": "Your suggestions...",
    "recommend": "Would you recommend this safari to your friends or family?",
    "rec1": "Definitely!",
    "rec2": "Maybe / I'll consider it.",
    "rec3": "No.",
    "comments": "Additional Comments",
    "commentsPh": "Please provide any further feedback or thoughts you would like to share with us.",
    "submitBtn": "Submit Feedback",
    "submitting": "Submitting...",
    "errSubmit": "Something went wrong while submitting. Please check your internet connection and try again.",
    "footerMsg": "Thank you for choosing our Jungle Safari!"
  },
  "hi": {
    "headerIntro": "हमारे साथ जुड़ने के लिए धन्यवाद! हम आपके अनुभव के बारे में जानना चाहेंगे। कृपया यह छोटा फीडबैक फॉर्म भरने के लिए कुछ समय निकालें।",
    "requiredNote": "* आवश्यक प्रश्न दर्शाता है",
    "successTitle": "आपके फीडबैक के लिए धन्यवाद!",
    "successMsg": "हमारी जंगल सफारी चुनने के लिए धन्यवाद! आशा है आपका अनुभव शानदार रहा। आपका दिन शुभ हो!",
    "submitAnother": "एक और प्रतिक्रिया भेजें",
    "visitorDetails": "आगंतुक विवरण",
    "visitorDetailsSub": "अपने बारे में और अपनी सफारी यात्रा के बारे में हमें बताएं।",
    "visitorName": "आगंतुक का नाम",
    "optional": "(वैकल्पिक)",
    "visitorNamePh": "अपना पूरा नाम लिखें",
    "occupation": "व्यवसाय",
    "occupationPh": "उदा. शिक्षक, किसान, व्यापार",
    "nationality": "राष्ट्रीयता",
    "nationalityPh": "उदा. भारतीय",
    "address": "पता",
    "addressPh": "अपना पता लिखें",
    "addressErr": "कृपया अपना पता लिखें।",
    "phone": "फोन / मोबाइल नंबर",
    "phonePh": "उदा. 9876543210",
    "phoneErr": "कृपया मान्य 10 अंकों का मोबाइल नंबर लिखें।",
    "safariDateTime": "सफारी की तारीख और समय",
    "safariDateTimeErr": "कृपया सफारी की तारीख और समय दोनों चुनें (तारीख भविष्य की नहीं हो सकती)।",
    "vehicleGuide": "वाहन नंबर / गाइड का नाम",
    "vehicleGuidePh": "उदा. MH-31-AB-1234 / रमेश",
    "vehicleGuideErr": "कृपया वाहन नंबर या गाइड का नाम लिखें।",
    "q1Title": "1. समग्र सफारी अनुभव",
    "q1Sub": "आप अपने समग्र जंगल सफारी अनुभव को कैसे आंकेंगे?",
    "optExcellent": "उत्कृष्ट",
    "optGood": "अच्छा",
    "optAverage": "औसत",
    "optPoor": "खराब",
    "selectErr": "कृपया एक विकल्प चुनें।",
    "q2Title": "2. हमारी सेवाओं को रेट करें",
    "q2Sub": "कृपया निम्नलिखित सेवाओं को रेट करें।",
    "scaleHint": "1 = बहुत खराब · 5 = उत्कृष्ट",
    "serviceCol": "सेवा",
    "svc_bookingProcess": "बुकिंग प्रक्रिया",
    "svc_vehicleCondition": "वाहन की स्थिति और आराम",
    "svc_guideKnowledge": "गाइड / ड्राइवर का ज्ञान और व्यवहार",
    "svc_safetyMeasures": "सुरक्षा उपाय",
    "svc_cleanliness": "स्वच्छता और सुविधाएं",
    "ratingsErr": "कृपया सभी पांच सेवाओं को रेट करें।",
    "q3Title": "3. वन्यजीव दर्शन",
    "q3Sub": "क्या आपने सफारी के दौरान वन्यजीव (जानवर/पक्षी) देखे?",
    "wl1": "हाँ, उम्मीद से ज़्यादा!",
    "wl2": "हाँ, कुछ देखे।",
    "wl3": "नहीं, मुश्किल से कोई देखा।",
    "q4Title": "4. आपका विस्तृत फीडबैक",
    "q4Sub": "सफारी को और बेहतर बनाने में हमारी मदद करें!",
    "likedMost": "इस सफारी में आपको सबसे ज़्यादा क्या पसंद आया?",
    "likedMostPh": "जो अच्छा लगा वह साझा करें...",
    "suggestions": "क्या हमारी सेवाओं को बेहतर बनाने के लिए आपके पास कोई सुझाव हैं?",
    "suggestionsPh": "आपके सुझाव...",
    "recommend": "क्या आप इस सफारी की सिफारिश अपने दोस्तों या परिवार को करेंगे?",
    "rec1": "बिल्कुल!",
    "rec2": "शायद / मैं सोचूंगा।",
    "rec3": "नहीं।",
    "comments": "अतिरिक्त टिप्पणियाँ",
    "commentsPh": "कृपया कोई अन्य फीडबैक या विचार हमारे साथ साझा करें।",
    "submitBtn": "फीडबैक भेजें",
    "submitting": "भेजा जा रहा है...",
    "errSubmit": "भेजते समय कुछ गलत हो गया। कृपया अपना इंटरनेट कनेक्शन जांचें और फिर से प्रयास करें।",
    "footerMsg": "हमारी जंगल सफारी चुनने के लिए धन्यवाद!"
  },
  "mr": {
    "headerIntro": "आमच्यासोबत सामील झाल्याबद्दल धन्यवाद! आम्हाला तुमच्या अनुभवाबद्दल जाणून घ्यायला आवडेल. कृपया हा छोटा फीडबॅक फॉर्म भरण्यासाठी थोडा वेळ द्या.",
    "requiredNote": "* आवश्यक प्रश्न दर्शवतो",
    "successTitle": "तुमच्या फीडबॅकसाठी धन्यवाद!",
    "successMsg": "आमची जंगल सफारी निवडल्याबद्दल धन्यवाद! तुमचा अनुभव छान झाला असेल अशी आशा आहे. तुमचा दिवस शुभ जावो!",
    "submitAnother": "आणखी एक प्रतिसाद पाठवा",
    "visitorDetails": "पर्यटक तपशील",
    "visitorDetailsSub": "तुमच्याबद्दल आणि तुमच्या सफारी सहलीबद्दल आम्हाला सांगा.",
    "visitorName": "पर्यटकाचे नाव",
    "optional": "(ऐच्छिक)",
    "visitorNamePh": "तुमचे पूर्ण नाव लिहा",
    "occupation": "व्यवसाय",
    "occupationPh": "उदा. शिक्षक, शेतकरी, व्यवसाय",
    "nationality": "राष्ट्रीयत्व",
    "nationalityPh": "उदा. भारतीय",
    "address": "पत्ता",
    "addressPh": "तुमचा पत्ता लिहा",
    "addressErr": "कृपया तुमचा पत्ता लिहा.",
    "phone": "फोन / मोबाईल नंबर",
    "phonePh": "उदा. 9876543210",
    "phoneErr": "कृपया वैध 10 अंकी मोबाईल नंबर लिहा.",
    "safariDateTime": "सफारीची तारीख आणि वेळ",
    "safariDateTimeErr": "कृपया सफारीची तारीख आणि वेळ दोन्ही निवडा (तारीख भविष्यातील असू शकत नाही).",
    "vehicleGuide": "वाहन क्रमांक / गाईडचे नाव",
    "vehicleGuidePh": "उदा. MH-31-AB-1234 / रमेश",
    "vehicleGuideErr": "कृपया वाहन क्रमांक किंवा गाईडचे नाव लिहा.",
    "q1Title": "1. एकूण सफारी अनुभव",
    "q1Sub": "तुम्ही तुमच्या एकूण जंगल सफारी अनुभवाला कसे रेट कराल?",
    "optExcellent": "उत्कृष्ट",
    "optGood": "चांगला",
    "optAverage": "साधारण",
    "optPoor": "वाईट",
    "selectErr": "कृपया एक पर्याय निवडा.",
    "q2Title": "2. आमच्या सेवांना रेटिंग द्या",
    "q2Sub": "कृपया खालील सेवांना रेटिंग द्या.",
    "scaleHint": "1 = खूप वाईट · 5 = उत्कृष्ट",
    "serviceCol": "सेवा",
    "svc_bookingProcess": "बुकिंग प्रक्रिया",
    "svc_vehicleCondition": "वाहनाची स्थिती आणि आराम",
    "svc_guideKnowledge": "गाईड / ड्रायव्हरचे ज्ञान आणि वर्तन",
    "svc_safetyMeasures": "सुरक्षा उपाय",
    "svc_cleanliness": "स्वच्छता आणि सुविधा",
    "ratingsErr": "कृपया सर्व पाच सेवांना रेटिंग द्या.",
    "q3Title": "3. वन्यजीव दर्शन",
    "q3Sub": "सफारी दरम्यान तुम्हाला वन्यजीव (प्राणी/पक्षी) दिसले का?",
    "wl1": "हो, अपेक्षेपेक्षा जास्त!",
    "wl2": "हो, काही दिसले.",
    "wl3": "नाही, जवळजवळ काहीच दिसले नाही.",
    "q4Title": "4. तुमचा सविस्तर फीडबॅक",
    "q4Sub": "सफारी आणखी चांगली करण्यासाठी आम्हाला मदत करा!",
    "likedMost": "या सफारीत तुम्हाला सर्वात जास्त काय आवडले?",
    "likedMostPh": "तुम्हाला काय आवडले ते सांगा...",
    "suggestions": "आमच्या सेवा सुधारण्यासाठी तुमच्याकडे काही सूचना आहेत का?",
    "suggestionsPh": "तुमच्या सूचना...",
    "recommend": "तुम्ही ही सफारी तुमच्या मित्रांना किंवा कुटुंबाला सुचवाल का?",
    "rec1": "नक्कीच!",
    "rec2": "कदाचित / विचार करेन.",
    "rec3": "नाही.",
    "comments": "अतिरिक्त टिप्पण्या",
    "commentsPh": "कृपया आणखी काही फीडबॅक किंवा विचार आमच्यासोबत शेअर करा.",
    "submitBtn": "फीडबॅक पाठवा",
    "submitting": "पाठवत आहे...",
    "errSubmit": "पाठवताना काहीतरी चूक झाली. कृपया तुमचे इंटरनेट कनेक्शन तपासा आणि पुन्हा प्रयत्न करा.",
    "footerMsg": "आमची जंगल सफारी निवडल्याबद्दल धन्यवाद!"
  }
}
